{
  "annotations": {
    "list": [
      {
        "builtIn": 1,
        "datasource": {
          "type": "grafana",
          "uid": "-- Grafana --"
        },
        "enable": true,
        "hide": true,
        "iconColor": "rgba(0, 211, 255, 1)",
        "name": "Annotations & Alerts",
        "type": "dashboard"
      }
    ]
  },
  "editable": true,
  "fiscalYearStartMonth": 0,
  "graphTooltip": 0,
  "id": null,
  "links": [],
  "panels": [
    {
      "datasource": {
        "type": "prometheus",
        "uid": "prometheus"
      },
      "fieldConfig": {
        "defaults": {
          "mappings": [],
          "thresholds": {
            "mode": "absolute",
            "steps": [
              { "color": "red", "value": null },
              { "color": "green", "value": 1 }
            ]
          },
          "unit": "none"
        },
        "overrides": []
      },
      "gridPos": {
        "h": 8,
        "w": 12,
        "x": 0,
        "y": 0
      },
      "id": 1,
      "options": {
        "colorMode": "value",
        "graphMode": "area",
        "justifyMode": "auto",
        "orientation": "auto",
        "percentChangeColorMode": "standard",
        "reduceOptions": {
          "calcs": ["lastNotNull"],
          "fields": "",
          "values": false
        },
        "showPercentChange": false,
        "textMode": "auto",
        "wideLayout": true
      },
      "pluginVersion": "12.0.0",
      "targets": [
        {
          "editorMode": "code",
          "expr": "probe_success",
          "legendFormat": "{{ instance }}",
          "range": true,
          "refId": "A"
        }
      ],
      "title": "Probe Success",
      "type": "stat"
    },
    {
      "datasource": {
        "type": "prometheus",
        "uid": "prometheus"
      },
      "fieldConfig": {
        "defaults": {
          "mappings": [],
          "unit": "s"
        },
        "overrides": []
      },
      "gridPos": {
        "h": 8,
        "w": 12,
        "x": 12,
        "y": 0
      },
      "id": 2,
      "options": {
        "legend": {
          "displayMode": "list",
          "placement": "bottom",
          "showLegend": true
        },
        "tooltip": {
          "mode": "single",
          "sort": "none"
        }
      },
      "pluginVersion": "12.0.0",
      "targets": [
        {
          "editorMode": "code",
          "expr": "probe_duration_seconds",
          "legendFormat": "{{ instance }}",
          "range": true,
          "refId": "A"
        }
      ],
      "title": "Probe Duration",
      "type": "timeseries"
    },
    {
      "datasource": {
        "type": "prometheus",
        "uid": "prometheus"
      },
      "fieldConfig": {
        "defaults": {
          "mappings": [],
          "unit": "percentunit"
        },
        "overrides": []
      },
      "gridPos": {
        "h": 9,
        "w": 24,
        "x": 0,
        "y": 8
      },
      "id": 3,
      "options": {
        "legend": {
          "displayMode": "list",
          "placement": "bottom",
          "showLegend": true
        },
        "tooltip": {
          "mode": "multi",
          "sort": "desc"
        }
      },
      "pluginVersion": "12.0.0",
      "targets": [
        {
          "editorMode": "code",
          "expr": "avg_over_time(probe_success[5m])",
          "legendFormat": "{{ instance }}",
          "range": true,
          "refId": "A"
        }
      ],
      "title": "Availability Last 5 Minutes",
      "type": "timeseries"
    }
  ],
  "refresh": "10s",
  "schemaVersion": 39,
  "tags": ["blackbox", "prometheus", "monitoring"],
  "templating": {
    "list": []
  },
  "time": {
    "from": "now-15m",
    "to": "now"
  },
  "timepicker": {},
  "timezone": "browser",
  "title": "Blackbox Monitoring Overview",
  "uid": "blackbox-monitoring-overview",
  "version": 1,
  "weekStart": ""
}